{
	"games_superfinal": [
		{
			"id": 0,
			"date": "09.11.2022",
			"time": "19:00",
			"teams": [
				{
					"id": 0,
					"name": "1 Место группы А",
					"city": "",
					"logo_url": "",
					"goal": -1,
					"group": 1
				},
				{
					"id": 1,
					"name": "1 Место группы Б",
					"city": "",
					"logo_url": "",
					"goal": -1,
					"group": 1
				}
			]
		},

		{
			"id": 1,
			"date": "10.11.2022",
			"time": "11:40",

			"teams": [
				{
					"id": 0,
					"name": "1 Место группы Б",
					"city": "",
					"logo_url": "",
					"goal": -1,
					"group": 2
				},
				{
					"id": 1,
					"name": "1 Место группы А",
					"city": "",
					"logo_url": "",
					"goal": -1,
					"group": 2
				}
			]
		}
	]
}
